lightTagger/__init__.py
lightTagger/predictor.py
lightTagger/models/__init__.py
lightTagger/models/utils.py
lightTagger/models/wd14_predictor.py
light_tagger/__init__.py
light_tagger/predictor.py
light_tagger/models/__init__.py
light_tagger/models/utils.py
light_tagger/models/wd14_predictor.py
light_tagger-0.0.2.dist-info/LICENSE
light_tagger-0.0.2.dist-info/METADATA
light_tagger-0.0.2.dist-info/WHEEL
light_tagger-0.0.2.dist-info/top_level.txt
light_tagger-0.0.2.dist-info/RECORD
