Metadata-Version: 2.1
Name: light-tagger
Version: 0.0.2
Summary: A package for tagging photo, all the tags will be combine to a sentence.
Author: bubbliiiing
Author-email: bubbliiiing@qq.com
License: Apache-2.0
Classifier: Development Status :: 1 - Planning
Classifier: Intended Audience :: Developers
Classifier: Programming Language :: Python :: 3
Classifier: Operating System :: Unix
Classifier: Operating System :: MacOS :: MacOS X
Classifier: Operating System :: Microsoft :: Windows
License-File: LICENSE
Requires-Dist: pillow (>=9.0.0)
Requires-Dist: requests (>=2.30.0)
Requires-Dist: opencv-python
Requires-Dist: onnxruntime-gpu
Requires-Dist: numpy
Requires-Dist: tqdm
